nkust_ucl/__init__.py
nkust_ucl/k12.py
nkust_ucl/utils/__init__.py
nkust_ucl/utils/attachment.py
nkust_ucl/utils/config.py
nkust_ucl/utils/log.py
nkust_ucl/utils/mqtt_client.py
nkust_ucl_k12_bot-2.9.2.dist-info/LICENSE
nkust_ucl_k12_bot-2.9.2.dist-info/METADATA
nkust_ucl_k12_bot-2.9.2.dist-info/WHEEL
nkust_ucl_k12_bot-2.9.2.dist-info/top_level.txt
nkust_ucl_k12_bot-2.9.2.dist-info/RECORD
