Metadata-Version: 2.1
Name: nkust-ucl-k12-bot
Version: 2.9.2
Summary: 一個用於k12的bot包
Home-page: https://github.com/xinbow99/k12-telegram
Author: Ethan Cheng
Author-email: asdewq45445@gmail.com
Classifier: Programming Language :: Python :: 3
Classifier: License :: OSI Approved :: MIT License
Classifier: Operating System :: OS Independent
License-File: LICENSE
Requires-Dist: paho-mqtt (==1.6.1)
Requires-Dist: PyYAML (==6.0)
Requires-Dist: requests (==2.28.2)
